Workbook
Name BSCheck: Model!$F$118
Name L_Scenarios: Scenarios!$D$12:$D$14
Name million: Assumptions!$F$12
Name S_Scenarios: Scenarios!$E$11
Name ScenarioUSed: Scenarios!$D$11

Sheet Cover
C7: Veritas Dwellings
C8: Financial Model for 2025 to 2029
C11: Modeller | D11: Animashaun Jafar
C12: Version | D12: Ver 1.01
C13: Circularity in Model | D13: Interest Expense Line of the P&L

Sheet Historicals FS
B2: Veritas Dwellings
B3: Income Statement
B5: ($ Millions)
G7: 2022 | H7: 2023 | I7: 2024
C9: Gross Revenue | G9: 1553.87 | H9: 1776.88 | I9: 1975.48
C11: Cost of Sales | G11: 980.84 | H11: 1078.03 | I11: 1201.29
C12: SG&A | G12: 265.79 | H12: 290.54 | I12: 305.35
C13: Total Costs | G13: 1246.63 | H13: 1368.57 | I13: 1506.64
C15: Cost Adjustments - Gain/(Loss) | G15: 0 | H15: 0 | I15: 0
C16: EBITDA | G16: 307.24 | H16: 408.31 | I16: 468.84
C18: Depreciation | G18: 25.539 | H18: 32.057 | I18: 38.499
C19: EBIT | G19: 281.701 | H19: 376.253 | I19: 430.341
C21: Interest Expense | G21: 13.304 | H21: 14.263 | I21: 22.055
C22: EBT | G22: 268.397 | H22: 361.99 | I22: 408.286
C24: Current Taxes | G24: 62.432 | H24: 92.477 | I24: 100.457
C25: Deferred Income Taxes | G25: 9.031 | H25: 2.745 | I25: 10.737
... C28: Net Income | G28: 196.934 | H28: 266.768 | I28: 297.092
B30: =B2 -> Veritas Dwellings
B31: Cash Flow Statement
B33: ($ Millions)
G35: 2015 | H35: 2016 | I35: 2017
B36: Operating Activities
C37: Net Income | G37: 196.934 | H37: 266.768 | I37: 297.092
C38: Depreciation | G38: 25.539 | H38: 32.057 | I38: 38.499
C39: Deferred Income Taxes | G39: 9.031 | H39: 2.745 | I39: 10.737
C40: Changes in Working Capital | G40: -5.847 | H40: -19.241 | I40: -2.397
C41: Other | G41: 11.584 | H41: 27.166 | I41: -7.151
C42: Operating Cash Flow | G42: 237.241 | H42: 309.495 | I42: 336.78
B44: Investing Activities
C45: CAPEX | G45: -56.626 | H45: -62.953 | I45: -110.809
C46: Other | G46: 0 | H46: 0 | I46: 0
C47: Investing Cash Flow | G47: -56.626 | H47: -62.953 | I47: -110.809
B49: Financing Activities
C50: Revolver Issuance / (Repayment) | G50: 10 | H50: 0 | I50: 0
C51: Variable Rate Long Term Debt Issuance / (Repayment) | G51: 100 | H51: 80 | I51: 350
C52: Fixed Rate Long Term Debt Issuance / (Repayment) | G52: 0 | H52: 156.67 | I52: -80
C53: Preference Shares Issuance/ (Buy-Back) | G53: 0 | H53: 0 | I53: 0
C54: Common Shares Issuance/ (Buy-Back) | G54: -282.813 | H54: -432.826 | I54: -461.157
C55: Preference Dividends | G55: 0 | H55: 0 | I55: 0
C56: Common Dividends | G56: -27.89 | H56: -30.077 | I56: -31.291
C57: Other Financing Activities | G57: -1.227 | H57: -1.321 | I57: -1.938
C58: Financing Cash Flow | G58: -201.93 | H58: -227.554 | I58: -224.386
C60: Change in Cash Position | G60: -21.315 | H60: 18.988 | I60: 1.585
C61: Beginning Cash | G61: 47.647 | H61: 26.332 | I61: 45.32
C62: Ending Cash | G62: 26.332 | H62: 45.32 | I62: 46.905
B67: =B2 -> Veritas Dwellings
B68: Balance Sheet
B70: ($ Millions)
G71: 2015 | H71: 2016 | I71: 2017
B72: ASSETS
C73: Cash and Equivalents | G73: 26.332 | H73: 45.32 | I73: 46.905
C74: Accounts Receivable | G74: 6.669 | H74: 7.412 | I74: 10.257
C75: Inventory | G75: 272.613 | H75: 313.463 | I75: 310.477
C76: Prepaid Expenses | G76: 0 | H76: 0 | I76: 0
C77: Other | G77: 59.481 | H77: 50.961 | I77: 10.633
C78: Total Current Assets | G78: =SUM(G73:G77) -> 365.095 | H78: =SUM(H73:H77) -> 417.156 | I78: =SUM(I73:I77) -> 378.272
C80: Net PP&E | G80: 199.602 | H80: 246.571 | I80: 318.878
C81: Goodwill | G81: 485.188 | H81: 485.188 | I81: 485.188
C82: Intangibles | G82: 89.384 | H82: 91.289 | I82: 93.01
C83: Other | G83: 0 | H83: 0 | I83: 0
C84: Total Long Term Assets | G84: =SUM(G80:G83) -> 774.174 | H84: =SUM(H80:H83) -> 823.048 | I84: =SUM(I80:I83) -> 897.076
C86: Total Assets | G86: =G78+G84 -> 1139.269 | H86: =H78+H84 -> 1240.204 | I86: =I78+I84 -> 1275.348
B88: LIABILITIES AND EQUITY
C89: Bank Debt - Revolver | G89: 10 | H89: 0 | I89: 0
C90: Accounts Payable | G90: 117.159 | H90: 110.781 | I90: 132.324
C91: Other | G91: 23.596 | H91: 38.209 | I91: 24.182
C92: Total Current Liabilities | G92: =SUM(G89:G91) -> 150.755 | H92: =SUM(H89:H91) -> 148.99 | I92: =SUM(I89:I91) -> 156.506
C94: Variable Rate Long Term Debt | G94: 100 | H94: 185.584 | I94: 183.223
C95: Fixed Rate Long Term Debt | G95: 260.46 | H95: 422.829 | I95: 704.055
C96: Deferred Income Taxes | G96: 93.04 | H96: 123.811 | I96: 110.157
C97: Other | G97: 41.361 | H97: 47.755 | I97: 54.551
C98: Total Long Term Liabilities | G98: =SUM(G94:G97) -> 494.861 | H98: =SUM(H94:H97) -> 779.979 | I98: =SUM(I94:I97) -> 1051.986
C100: Total Liabilities | G100: =G92+G98 -> 645.616 | H100: =H92+H98 -> 928.969 | I100: =I92+I98 -> 1208.492
C102: Preference Shares | G102: 0 | H102: 0 | I102: 0
C103: Common Shares | G103: 308.489 | H103: 292.864 | I103: 280.177
C104: Retained Earnings | G104: 130.741 | H104: -41.583 | I104: -228.638
C105: Other | G105: 54.423 | H105: 59.954 | I105: 15.317
C106: Shareholder's Equity | G106: =SUM(G102:G105) -> 493.653 | H106: =SUM(H102:H105) -> 311.235 | I106: =SUM(I102:I105) -> 66.856
B108: Total Liabilities and Equity | G108: =G100+G106 -> 1139.269 | H108: =H100+H106 -> 1240.204 | I108: =I100+I106 -> 1275.348

Sheet Summary
B2: =Cover!$C$7 -> Veritas Dwellings | I2: ="Financial Forecast: "&L6&" to "&P6 -> Financial Forecast: 2025 to 2029
B3: Summary | I3: =IF(BSCheck=0,"BS Check: OK","BS Check: ERROR") -> BS Check: OK | K3: =ScenarioUSed -> Scenario: Base Case
I5: Actual | J5: Actual | K5: Actual | L5: Forecast | M5: Forecast | N5: Forecast | O5: Forecast | P5: Forecast
E6: Units | F6: Trend | I6: ='Historicals FS'!G7 -> 2022 | J6: ='Historicals FS'!H7 -> 2023 | K6: ='Historicals FS'!I7 -> 2024 | L6: =K6+1 -> 2025 | M6: =L6+1 -> 2026 | N6: =M6+1 -> 2027 | O6: =N6+1 -> 2028 | P6: =O6+1 -> 2029
B8: Analysis Based on : Base Case Scenario
C10: Revenue
D11: Gross Revenue | E11: $'m | I11: 1553.87 | J11: 1776.88 | K11: 1975.48 | L11: 2113.2846 | M11: 2284.545 | N11: 2464.179 | O11: 2623.9274 | P11: 2820.5087
D12: Growth Rate | E12: % | J12: 0.14351908 | K12: 0.11176894 | L12: 0.069757518 | M12: 0.081039907 | N12: 0.078630123 | O12: 0.064828223 | P12: 0.074918756
C13: EBITDA
D14: EBITDA | E14: $'m | I14: 307.24 | J14: 408.31 | K14: 468.84 | L14: 490.46089 | M14: 522.52323 | N14: 553.09649 | O14: 569.28494 | P14: 595.92611
D15: Growth Rate | E15: % | J15: 0.32896107 | K15: 0.14824521 | L15: 0.046115715 | M15: 0.065371852 | N15: 0.058510811 | O15: 0.029268763 | P15: 0.046797612
D16: EBITA Margin | E16: % | I16: 0.19772568 | J16: 0.22979042 | K16: 0.23732966 | L16: 0.23208464 | M16: 0.22872092 | N16: 0.22445467 | O16: 0.21695911 | P16: 0.2112832
C17: Net Profit
D18: Net Profit | E18: $'m | I18: 196.934 | J18: 266.768 | K18: 297.092 | L18: 310.1297 | M18: 328.87209 | N18: 346.77191 | O18: 354.38005 | P18: 368.58605
D19: Growth Rate | E19: % | J19: 0.35460611 | K19: 0.1136718 | L19: 0.043884394 | M19: 0.060434034 | N19: 0.054427894 | O19: 0.021939915 | P19: 0.040086905
D20: Net Profit Margin | E20: % | I20: 0.12673776 | J20: 0.15013282 | K20: 0.15038978 | L20: 0.14675246 | M20: 0.14395518 | N20: 0.14072513 | O20: 0.13505711 | P20: 0.1306807
C21: Dupont Analysis
D22: ROE | E22: % | I22: 0.39893204 | J22: 0.85712725 | K22: 4.4437597 | L22: 0.88205322 | M22: 0.50753633 | N22: 0.36299223 | O22: 0.28005843 | P22: 0.23277436
D23: Net Profit Margin | E23: % | I23: 0.12673776 | J23: 0.15013282 | K23: 0.15038978 | L23: 0.14675246 | M23: 0.14395518 | N23: 0.14072513 | O23: 0.13505711 | P23: 0.1306807
D24: Asset Turnover | E24: times | I24: 1.3639184 | J24: 1.432732 | K24: 1.5489733 | L24: 1.5284396 | M24: 1.56119 | N24: 1.5198875 | O24: 1.4493246 | P24: 1.3715254
D25: Financial Leverage | E25: times | I25: 2.3078336 | J25: 3.9847832 | K25: 19.076044 | L25: 3.9324312 | M25: 2.2583127 | N25: 1.6971266 | O25: 1.4307558 | P25: 1.2987328
B27: Analysis Based on : Best Case Scenario
C29: Revenue
D30: Gross Revenue | E30: $'m | I30: 1553.87 | J30: 1776.88 | K30: 1975.48 | L30: 2160.2361 | M30: 2384.1036 | N30: 2622.4241 | O30: 2846.2607 | P30: 3114.7328
D31: Growth Rate | E31: % | J31: 0.14351908 | K31: 0.11176894 | L31: 0.093524684 | M31: 0.10363102 | N31: 0.099962304 | O31: 0.085354861 | P31: 0.094324462
C32: EBITDA
D33: EBITDA | E33: $'m | I33: 307.24 | J33: 408.31 | K33: 468.84 | L33: 536.12888 | M33: 623.83671 | N33: 717.70335 | O33: 803.74725 | P33: 910.43363
D34: Growth Rate | E34: % | J34: 0.32896107 | K34: 0.14824521 | L34: 0.14352206 | M34: 0.16359466 | N34: 0.15046669 | O34: 0.11988783 | P34: 0.13273623
D35: EBITA Margin | E35: % | I35: 0.19772568 | J35: 0.22979042 | K35: 0.23732966 | L35: 0.24818068 | M35: 0.2616651 | N35: 0.27367936 | O35: 0.28238707 | P35: 0.29229911
C36: Net Profit
D37: Net Profit | E37: $'m | I37: 196.934 | J37: 266.768 | K37: 297.092 | L37: 341.18394 | M37: 397.76526 | N37: 458.70457 | O37: 513.81442 | P37: 582.45116
D38: Growth Rate | E38: % | J38: 0.35460611 | K38: 0.1136718 | L38: 0.14841173 | M38: 0.16583817 | N38: 0.15320422 | O38: 0.12014236 | P38: 0.13358274
D39: Net Profit Margin | E39: % | I39: 0.12673776 | J39: 0.15013282 | K39: 0.15038978 | L39: 0.15793826 | M39: 0.16684059 | N39: 0.17491624 | O39: 0.18052261 | P39: 0.18699876
C40: Dupont Analysis
D41: ROE | E41: % | I41: 0.39893204 | J41: 0.85712725 | K41: 4.4437597 | L41: 0.90633589 | M41: 0.54642937 | N41: 0.40780301 | O41: 0.32885585 | P41: 0.28390212
D42: Net Profit Margin | E42: % | I42: 0.12673776 | J42: 0.15013282 | K42: 0.15038978 | L42: 0.15793826 | M42: 0.16684059 | N42: 0.17491624 | O42: 0.18052261 | P42: 0.18699876
D43: Asset Turnover | E43: times | I43: 1.3639184 | J43: 1.432732 | K43: 1.5489733 | L43: 1.5616992 | M43: 1.5733392 | N43: 1.4643549 | O43: 1.3506839 | P43: 1.2341249
D44: Financial Leverage | E44: times | I44: 2.3078336 | J44: 3.9847832 | K44: 19.076044 | L44: 3.6745524 | M44: 2.0816607 | N44: 1.5921132 | O44: 1.3487151 | P44: 1.230186
B47: Analysis Based on : Worst Case Scenario
C49: Revenue
D50: Gross Revenue | E50: $'m | I50: 1553.87 | J50: 1776.88 | K50: 1975.48 | L50: 2066.8414 | M50: 2187.5114 | N50: 2312.1815 | O50: 2413.4506 | P50: 2545.9087
D51: Growth Rate | E51: % | J51: 0.14351908 | K51: 0.11176894 | L51: 0.046247682 | M51: 0.058383791 | N51: 0.056991749 | O51: 0.043798094 | P51: 0.054883263
C52: EBITDA
D53: EBITDA | E53: $'m | I53: 307.24 | J53: 408.31 | K53: 468.84 | L53: 433.28835 | M53: 394.39246 | N53: 345.16182 | O53: 274.22679 | P53: 201.54614
D54: Growth Rate | E54: % | J54: 0.32896107 | K54: 0.14824521 | L54: -0.075828959 | M54: -0.089769064 | N54: -0.12482654 | O54: -0.20551238 | P54: -0.26503849
D55: EBITA Margin | E55: % | I55: 0.19772568 | J55: 0.22979042 | K55: 0.23732966 | L55: 0.20963793 | M55: 0.18029276 | N55: 0.14927972 | O55: 0.11362436 | P55: 0.079164715
C56: Net Profit
D57: Net Profit | E57: $'m | I57: 196.934 | J57: 266.768 | K57: 297.092 | L57: 271.25237 | M57: 241.74317 | N57: 205.37633 | O57: 153.74051 | P57: 100.40767
D58: Growth Rate | E58: % | J58: 0.35460611 | K58: 0.1136718 | L58: -0.086975164 | M58: -0.10878874 | N58: -0.15043585 | O58: -0.25142049 | P58: -0.3469017
D59: Net Profit Margin | E59: % | I59: 0.12673776 | J59: 0.15013282 | K59: 0.15038978 | L59: 0.13124005 | M59: 0.11051059 | N59: 0.08882362 | O59: 0.063701536 | P59: 0.039438833
C60: Dupont Analysis
D61: ROE | E61: % | I61: 0.39893204 | J61: 0.85712725 | K61: 4.4437597 | L61: 0.84634681 | M61: 0.44180436 | N61: 0.27701394 | O61: 0.17255875 | P61: 0.1009658
D62: Net Profit Margin | E62: % | I62: 0.12673776 | J62: 0.15013282 | K62: 0.15038978 | L62: 0.13124005 | M62: 0.11051059 | N62: 0.08882362 | O62: 0.063701536 | P62: 0.039438833
D63: Asset Turnover | E63: times | I63: 1.3639184 | J63: 1.432732 | K63: 1.5489733 | L63: 1.4914325 | M63: 1.487423 | N63: 1.478455 | O63: 1.441894 | P63: 1.4171591
D64: Financial Leverage | E64: times | I64: 2.3078336 | J64: 3.9847832 | K64: 19.076044 | L64: 4.3239269 | M64: 2.6877669 | N64: 2.1094297 | O64: 1.8786841 | P64: 1.8064737
A66: Summary Generator:
B67: ="Analysis Based on : "&INDEX(L_Scenarios,S_Scenarios)&" Scenario" -> Analysis Based on : Base Case Scenario
C69: Revenue
D70: =Model!D12 -> Gross Revenue | E70: $'m | I70: =Model!I12 -> 1553.87 | J70: =Model!J12 -> 1776.88 | K70: =Model!K12 -> 1975.48 | L70: =Model!L12 -> 2145.7711 | M70: =Model!M12 -> 2400.7401 | N70: =Model!N12 -> 2688.7075 | O70: =Model!O12 -> 3012.0125 | P70: =Model!P12 -> 3393.9499
D71: Growth Rate | E71: % | J71: =J70/I70-1 -> 0.14351908 | K71: =K70/J70-1 -> 0.11176894 | L71: =L70/K70-1 -> 0.086202406 | M71: =M70/L70-1 -> 0.11882396 | N71: =N70/M70-1 -> 0.1199494 | O71: =O70/N70-1 -> 0.12024552 | P71: =P70/O70-1 -> 0.1268047
C72: EBITDA
D73: =Model!D19 -> EBITDA | E73: $'m | I73: =Model!I19 -> 307.24 | J73: =Model!J19 -> 408.31 | K73: =Model!K19 -> 468.84 | L73: =Model!L19 -> 546.39728 | M73: =Model!M19 -> 677.48014 | N73: =Model!N19 -> 827.87195 | O73: =Model!O19 -> 999.22661 | P73: =Model!P19 -> 1204.3752
D74: Growth Rate | E74: % | J74: =J73/I73-1 -> 0.32896107 | K74: =K73/J73-1 -> 0.14824521 | L74: =L73/K73-1 -> 0.16542377 | M74: =M73/L73-1 -> 0.23990393 | N74: =N73/M73-1 -> 0.22198705 | O74: =O73/N73-1 -> 0.20698207 | P74: =P73/O73-1 -> 0.20530735
D75: =Model!D35 -> EBITA Margin | E75: % | I75: =Model!I35 -> 0.19772568 | J75: =Model!J35 -> 0.22979042 | K75: =Model!K35 -> 0.23732966 | L75: =Model!L35 -> 0.25463912 | M75: =Model!M35 -> 0.28219636 | N75: =Model!N35 -> 0.30790704 | O75: =Model!O35 -> 0.33174716 | P75: =Model!P35 -> 0.35485945
C76: Net Profit
D77: Net Profit | E77: $'m | I77: =Model!I31 -> 196.934 | J77: =Model!J31 -> 266.768 | K77: =Model!K31 -> 297.092 | L77: =Model!L31 -> 307.7706 | M77: =Model!M31 -> 400.21576 | N77: =Model!N31 -> 509.27227 | O77: =Model!O31 -> 634.65529 | P77: =Model!P31 -> 785.34672
D78: Growth Rate | E78: % | J78: =J77/I77-1 -> 0.35460611 | K78: =K77/J77-1 -> 0.1136718 | L78: =L77/K77-1 -> 0.035943731 | M78: =M77/L77-1 -> 0.30037037 | N78: =N77/M77-1 -> 0.27249428 | O78: =O77/N77-1 -> 0.24620036 | P78: =P77/O77-1 -> 0.23743823
D79: =Model!D38 -> Net Profit Margin | E79: % | I79: =Model!I38 -> 0.12673776 | J79: =Model!J38 -> 0.15013282 | K79: =Model!K38 -> 0.15038978 | L79: =Model!L38 -> 0.14343123 | M79: =Model!M38 -> 0.16670516 | N79: =Model!N38 -> 0.18941156 | O79: =Model!O38 -> 0.21070805 | P79: =Model!P38 -> 0.23139609
C80: Dupont Analysis
D81: =Model!D37 -> ROE | E81: % | I81: =Model!I37 -> 0.39893204 | J81: =Model!J37 -> 0.85712725 | K81: =Model!K37 -> 4.4437597 | L81: =Model!L37 -> 0.97616957 | M81: =Model!M37 -> 0.63461262 | N81: =Model!N37 -> 0.49665719 | O81: =Model!O37 -> 0.41980347 | P81: =Model!P37 -> 0.37241377
D82: =Model!D38 -> Net Profit Margin | E82: % | I82: =Model!I38 -> 0.12673776 | J82: =Model!J38 -> 0.15013282 | K82: =Model!K38 -> 0.15038978 | L82: =Model!L38 -> 0.14343123 | M82: =Model!M38 -> 0.16670516 | N82: =Model!N38 -> 0.18941156 | O82: =Model!O38 -> 0.21070805 | P82: =Model!P38 -> 0.23139609
D83: =Model!D39 -> Asset Turnover | E83: times | I83: =Model!I39 -> 1.3639184 | J83: =Model!J39 -> 1.432732 | K83: =Model!K39 -> 1.5489733 | L83: =Model!L39 -> 1.6138316 | M83: =Model!M39 -> 1.7454158 | N83: =Model!N39 -> 1.6739708 | O83: =Model!O39 -> 1.5352803 | P83: =Model!P39 -> 1.3069383
D84: =Model!D40 -> Financial Leverage | E84: times | I84: =Model!I40 -> 2.3078336 | J84: =Model!J40 -> 3.9847832 | K84: =Model!K40 -> 19.076044 | L84: =Model!L40 -> 4.2171915 | M84: =Model!M40 -> 2.1810256 | N84: =Model!N40 -> 1.5663989 | O84: =Model!O40 -> 1.2977087 | P84: =Model!P40 -> 1.2314439

Sheet Assumptions
B2: =Cover!$C$7 -> Veritas Dwellings | I2: ="Financial Forecast: "&L6&" to "&P6 -> Financial Forecast: 2025 to 2029
B3: Inputs & Assumptions | I3: =IF(BSCheck=0,"BS Check: OK","BS Check: ERROR") -> BS Check: OK | K3: =ScenarioUSed -> Scenario: Base Case
I5: Actual | J5: Actual | K5: Actual | L5: Forecast | M5: Forecast | N5: Forecast | O5: Forecast | P5: Forecast
E6: Units | F6: Inputs | I6: ='Historicals FS'!G7 -> 2022 | J6: ='Historicals FS'!H7 -> 2023 | K6: ='Historicals FS'!I7 -> 2024 | L6: =K6+1 -> 2025 | M6: =L6+1 -> 2026 | N6: =M6+1 -> 2027 | O6: =N6+1 -> 2028 | P6: =O6+1 -> 2029
B9: General Assumptions
D11: Days in the Year | I11: =DATE(I6,12,31)-DATE(I6,1,1)+1 -> 365 | J11: =DATE(J6,12,31)-DATE(J6,1,1)+1 -> 365 | K11: =DATE(K6,12,31)-DATE(K6,1,1)+1 -> 366 | L11: =DATE(L6,12,31)-DATE(L6,1,1)+1 -> 365 | M11: =DATE(M6,12,31)-DATE(M6,1,1)+1 -> 365 | N11: =DATE(N6,12,31)-DATE(N6,1,1)+1 -> 365 | O11: =DATE(O6,12,31)-DATE(O6,1,1)+1 -> 366 | P11: =DATE(P6,12,31)-DATE(P6,1,1)+1 -> 365
D12: Millions | E12: Constant | F12: 1000000
C14: Style Guide
D16: Number | E16: Number | F16: 1234.5
D17: Input | E17: Number
D18: Percent | E18: Percent | F18: 0.23
D19: Multiples | E19: Number | F19: 12.5
D20: Linked Cell | E20: Number
D21: Units | E21: Text | F21: Text
D22: Headings 1 | E22: Text | F22: TEXT
D23: Headings 2 | E23: Text | F23: Text
D24: Headings 3 | E24: Text | F24: Text
B27: Revenue Assumptions
C29: Core Revenue Assumptions
D31: Number of Warehouses | E31: units | K31: 510
D32: Total Lettable Space | E32: sqm | K32: 5205000
D33: Square Meters per Store | E33: sqm | K33: =K32/K31 -> 10205.882
D34: Total Revenue | E34: $'m | K34: ='Historicals FS'!I9 -> 1975.48
D35: Auxiliary Revenue | E35: $'m | K35: 143
D36: Core Revenue | E36: $'m | K36: =K34-K35 -> 1832.48
D37: Sales Price per sqm | E37: $ | K37: =K36*million/K32 -> 352.06148
D39: Increase in Sales Price per sqm | E39: % | L39: =Scenarios!L26 -> 0.03 | M39: =Scenarios!M26 -> 0.03 | N39: =Scenarios!N26 -> 0.03 | O39: =Scenarios!O26 -> 0.03 | P39: =Scenarios!P26 -> 0.03
D41: Additional Warehouses | E41: units | L41: =Scenarios!L19 -> 30 | M41: =Scenarios!M19 -> 50 | N41: =Scenarios!N19 -> 55 | O41: =Scenarios!O19 -> 60 | P41: =Scenarios!P19 -> 70
B44: Production Cost Assumptions
D46: Cost of Sales | E46: $'m | K46: ='Historicals FS'!I11 -> 1201.29
D47: Variable Cost | E47: $'m | K47: 0.75
D48: Fixed Cost | E48: $'m | K48: =1-K47 -> 0.25
D49: Variable cost per Warehouse | E49: $'m | K49: =K46*K47/K31 -> 1.7666029
D50: Fixed Cost | E50: $'m | K50: =K46*K48 -> 300.3225
D52: SG& A | E52: $'m | L52: 320
D54: Cost inflation | E54: % | L54: =Scenarios!L33 -> 0.02 | M54: =Scenarios!M33 -> 0.02 | N54: =Scenarios!N33 -> 0.02 | O54: =Scenarios!O33 -> 0.02 | P54: =Scenarios!P33 -> 0.02
B57: Capex & Depreciation Assumptions
C59: Capex
D60: Additions | E60: $'m | L60: 50 | M60: 40 | N60: 50 | O60: 60 | P60: 70
D61: Depreciation Method | E61: Straight Line
C63: Useful Life of Assets
D64: Remaining Assets | E64: Years | F64: 11
D65: New Assets | E65: Years | F65: 21
B68: Working Capital Assumptions
D70: Days in the Year | E70: Days | I70: =I11 -> 365 | J70: =J11 -> 365 | K70: =K11 -> 366
C72: Extract from Financials
D73: Revenue | E73: $'m | I73: ='Historicals FS'!G9 -> 1553.87 | J73: ='Historicals FS'!H9 -> 1776.88 | K73: ='Historicals FS'!I9 -> 1975.48
D74: Cost of Sales | E74: $'m | I74: ='Historicals FS'!G11 -> 980.84 | J74: ='Historicals FS'!H11 -> 1078.03 | K74: ='Historicals FS'!I11 -> 1201.29
C76: Balances
D77: ='Historicals FS'!C74 -> Accounts Receivable | E77: $'m | I77: ='Historicals FS'!G74 -> 6.669 | J77: ='Historicals FS'!H74 -> 7.412 | K77: ='Historicals FS'!I74 -> 10.257
D78: ='Historicals FS'!C75 -> Inventory | E78: $'m | I78: ='Historicals FS'!G75 -> 272.613 | J78: ='Historicals FS'!H75 -> 313.463 | K78: ='Historicals FS'!I75 -> 310.477
D79: ='Historicals FS'!C76 -> Prepaid Expenses | E79: $'m | I79: ='Historicals FS'!G76 -> 0 | J79: ='Historicals FS'!H76 -> 0 | K79: ='Historicals FS'!I76 -> 0
D80: Other Assets | E80: $'m | I80: ='Historicals FS'!G77 -> 59.481 | J80: ='Historicals FS'!H77 -> 50.961 | K80: ='Historicals FS'!I77 -> 10.633
D81: ='Historicals FS'!C90 -> Accounts Payable | E81: $'m | I81: ='Historicals FS'!G90 -> 117.159 | J81: ='Historicals FS'!H90 -> 110.781 | K81: ='Historicals FS'!I90 -> 132.324
D82: Other Liabilities | E82: $'m | I82: ='Historicals FS'!G91 -> 23.596 | J82: ='Historicals FS'!H91 -> 38.209 | K82: ='Historicals FS'!I91 -> 24.182
C84: Days
D85: =D77 -> Accounts Receivable | E85: Days | I85: =I77/I73*I$70 -> 1.5665307 | J85: =J77/J73*J$70 -> 1.5225451 | K85: =K77/K73*K$70 -> 1.900329 | L85: 1.663 | M85: 1.663 | N85: 1.663 | O85: 1.663 | P85: 1.663
D86: =D78 -> Inventory | E86: Days | I86: =I78/I$74*I$70 -> 101.44748 | J86: =J78/J$74*J$70 -> 106.13248 | K86: =K78/K$74*K$70 -> 94.593797 | L86: 100.735 | M86: 100.735 | N86: 100.735 | O86: 100.735 | P86: 100.735
D87: =D79 -> Prepaid Expenses | E87: Days | I87: =I79/I$74*I$70 -> 0 | J87: =J79/J$74*J$70 -> 0 | K87: =K79/K$74*K$70 -> 0 | L87: 0 | M87: 0 | N87: 0 | O87: 0 | P87: 0
D88: =D80 -> Other Assets | E88: Days | I88: =I80/I$74*I$70 -> 22.134665 | J88: =J80/J$74*J$70 -> 17.254404 | K88: =K80/K$74*K$70 -> 3.2395824 | L88: 14.222 | M88: 14.222 | N88: 14.222 | O88: 14.222 | P88: 14.222
D89: =D81 -> Accounts Payable | E89: Days | I89: =I81/I$74*I$70 -> 43.59838 | J89: =J81/J$74*J$70 -> 37.508293 | K89: =K81/K$74*K$70 -> 40.315481 | L89: 40.472 | M89: 40.472 | N89: 40.472 | O89: 40.472 | P89: 40.472
D90: =D82 -> Other Liabilities | E90: Days | I90: =I82/I$74*I$70 -> 8.7807797 | J90: =J82/J$74*J$70 -> 12.936825 | K90: =K82/K$74*K$70 -> 7.3675898 | L90: 9.7 | M90: 9.7 | N90: 9.7 | O90: 9.7 | P90: 9.7
B93: Taxation Assumptions
D95: Company Tax Rate | E95: % | F95: 0.35
D97: Reduction in EBT due to timing Diff | E97: $'m | L97: 40 | M97: 40 | N97: 40 | O97: 40 | P97: 40
B100: Debt & Interest Rate Assumptions
C102: Interest rates
D103: Excess Cash | E103: % | F103: 0.06 | L103: =$F103 -> 0.06 | M103: =$F103 -> 0.06 | N103: =$F103 -> 0.06 | O103: =$F103 -> 0.06 | P103: =$F103 -> 0.06
D104: Fixed Rate Senior Secured Debt | E104: % | F104: 0.0575 | L104: =$F104 -> 0.0575 | M104: =$F104 -> 0.0575 | N104: =$F104 -> 0.0575 | O104: =$F104 -> 0.0575 | P104: =$F104 -> 0.0575
D105: Revolver | E105: % | F105: 0.0575 | L105: =$F105 -> 0.0575 | M105: =$F105 -> 0.0575 | N105: =$F105 -> 0.0575 | O105: =$F105 -> 0.0575 | P105: =$F105 -> 0.0575
D107: NIBOR | E107: % | L107: 0.03 | M107: 0.035 | N107: 0.045 | O107: 0.04 | P107: 0.04
D108: Premium on Variable Rate Term Debt | E108: % | L108: 0.025 | M108: 0.025 | N108: 0.025 | O108: 0.025 | P108: 0.025
C110: Debt Repayment
D111: Amortisation on Fixed Senior secured Debt | E111: $'m | L111: 180 | M111: 180 | N111: 180 | O111: 180 | P111: 180
D112: Amortisation on Variable Senior secured Debt | E112: $'m | L112: 90 | M112: 90 | N112: 90 | O112: 90 | P112: 90
D114: Company will draw on Revolver if it needs to through a cash sweep
B116: Equity Assumptions
C118: Common Shares
D119: Common Share Issuance / (Buy-Back) | E119: $'m | L119: -20 | M119: -20 | N119: -20 | O119: -20 | P119: -20
D121: Stock Price | E121: $ | F121: 5
D122: Dividend Pay-out Ratio | E122: % | F122: 0.25 | L122: =$F$122 -> 0.25 | M122: =$F$122 -> 0.25 | N122: =$F$122 -> 0.25 | O122: =$F$122 -> 0.25 | P122: =$F$122 -> 0.25
C124: Common Shares
D125: Preference Share Issuance / (Buy-Back) | E125: $'m | L125: 40 | M125: 40 | N125: 40 | O125: 40 | P125: 40
D126: Dividend Pay-out Ratio | E126: % | F126: 0.08 | L126: =$F$126 -> 0.08 | M126: =$F$126 -> 0.08 | N126: =$F$126 -> 0.08 | O126: =$F$126 -> 0.08 | P126: =$F$126 -> 0.08
B128: Other Assumptions
D130: Cost inflation | E130: % | L130: =Scenarios!L33 -> 0.02 | M130: =Scenarios!M33 -> 0.02 | N130: =Scenarios!N33 -> 0.02 | O130: =Scenarios!O33 -> 0.02 | P130: =Scenarios!P33 -> 0.02
D132: Cost Adjustments - Gain/(Loss) | E132: $'m | L132: 0 | M132: 0 | N132: 0 | O132: 0 | P132: 0
D134: Change in Goodwill: Addition / (impairement) | E134: $'m | L134: 0 | M134: 0 | N134: 0 | O134: 0 | P134: 0
D135: Change in Intangible Assets: Additions / (Reduction) | E135: $'m | L135: 0 | M135: 0 | N135: 0 | O135: 0 | P135: 0
D136: Change in Other Equity: Additions / (Reduction) | E136: $'m | L136: 0 | M136: 0 | N136: 0 | O136: 0 | P136: 0
D137: Change in Other Operating Activities: Additions / (Reduction) | E137: $'m | L137: 0 | M137: 0 | N137: 0 | O137: 0 | P137: 0
D138: Change in Other Investing Activities: Additions / (Reduction) | E138: $'m | L138: 0 | M138: 0 | N138: 0 | O138: 0 | P138: 0
D139: Change in Other Financing Activities: Additions / (Reduction) | E139: $'m | L139: 0 | M139: 0 | N139: 0 | O139: 0 | P139: 0

Sheet Scenarios
B2: =Cover!$C$7 -> Veritas Dwellings | I2: ="Financial Forecast: "&L6&" to "&P6 -> Financial Forecast: 2025 to 2029
B3: Scenario Analysis | I3: =IF(BSCheck=0,"BS Check: OK","BS Check: ERROR") -> BS Check: OK | K3: =ScenarioUSed -> Scenario: Base Case
I5: Actual | J5: Actual | K5: Actual | L5: Forecast | M5: Forecast | N5: Forecast | O5: Forecast | P5: Forecast
E6: Units | F6: Inputs | I6: ='Historicals FS'!G7 -> 2022 | J6: ='Historicals FS'!H7 -> 2023 | K6: ='Historicals FS'!I7 -> 2024 | L6: =K6+1 -> 2025 | M6: =L6+1 -> 2026 | N6: =M6+1 -> 2027 | O6: =N6+1 -> 2028 | P6: =O6+1 -> 2029
B9: Scenario Used
D11: ="Scenario: "&INDEX(L_Scenarios,S_Scenarios) -> Scenario: Base Case | E11: 1
D12: Base Case
D13: Best Case
D14: Worst Case
B17: Additional Warehouses Scenarios
D19: Used in the Model | E19: Units | L19: =INDEX(L20:L22,S_Scenarios) -> 30 | M19: =INDEX(M20:M22,S_Scenarios) -> 50 | N19: =INDEX(N20:N22,S_Scenarios) -> 55 | O19: =INDEX(O20:O22,S_Scenarios) -> 60 | P19: =INDEX(P20:P22,S_Scenarios) -> 70
D20: =D$12 -> Base Case | E20: Units | L20: 30 | M20: 50 | N20: 55 | O20: 60 | P20: 70
D21: =D$13 -> Best Case | E21: Units | L21: 40 | M21: 60 | N21: 65 | O21: 70 | P21: 80
D22: =D$14 -> Worst Case | E22: Units | L22: 20 | M22: 40 | N22: 45 | O22: 50 | P22: 60
B24: Sales Price Inflation Scenarios
D26: Used in the Model | E26: % | L26: =INDEX(L27:L29,S_Scenarios) -> 0.03 | M26: =INDEX(M27:M29,S_Scenarios) -> 0.03 | N26: =INDEX(N27:N29,S_Scenarios) -> 0.03 | O26: =INDEX(O27:O29,S_Scenarios) -> 0.03 | P26: =INDEX(P27:P29,S_Scenarios) -> 0.03
D27: Base Case | E27: % | L27: 0.03 | M27: 0.03 | N27: 0.03 | O27: 0.03 | P27: 0.03
D28: Best Case | E28: % | L28: 0.04 | M28: 0.04 | N28: 0.04 | O28: 0.04 | P28: 0.04
D29: Worst Case | E29: % | L29: 0.02 | M29: 0.02 | N29: 0.02 | O29: 0.02 | P29: 0.02
B31: Cost Inflation Scenario
D33: Used in the Model | E33: % | L33: =INDEX(L34:L36,S_Scenarios) -> 0.02 | M33: =INDEX(M34:M36,S_Scenarios) -> 0.02 | N33: =INDEX(N34:N36,S_Scenarios) -> 0.02 | O33: =INDEX(O34:O36,S_Scenarios) -> 0.02 | P33: =INDEX(P34:P36,S_Scenarios) -> 0.02
D34: Base Case | E34: % | L34: 0.02 | M34: 0.02 | N34: 0.02 | O34: 0.02 | P34: 0.02
D35: Best Case | E35: % | L35: 0.01 | M35: 0.01 | N35: 0.01 | O35: 0.01 | P35: 0.01
D36: Worst Case | E36: % | L36: 0.03 | M36: 0.03 | N36: 0.03 | O36: 0.03 | P36: 0.03

Sheet Model
B2: =Cover!$C$7 -> Veritas Dwellings | I2: ="Financial Forecast: "&L6&" to "&P6 -> Financial Forecast: 2025 to 2029
B3: Model & Schedules | I3: =IF(BSCheck=0,"BS Check: OK","BS Check: ERROR") -> BS Check: OK | K3: =ScenarioUSed -> Scenario: Base Case
I5: Actual | J5: Actual | K5: Actual | L5: Forecast | M5: Forecast | N5: Forecast | O5: Forecast | P5: Forecast
E6: Units | F6: Inputs | I6: ='Historicals FS'!G7 -> 2022 | J6: ='Historicals FS'!H7 -> 2023 | K6: ='Historicals FS'!I7 -> 2024 | L6: =K6+1 -> 2025 | M6: =L6+1 -> 2026 | N6: =M6+1 -> 2027 | O6: =N6+1 -> 2028 | P6: =O6+1 -> 2029
A8: FINANCIAL STATEMENTS
B10: Income Statement
D12: ='Historicals FS'!C9 -> Gross Revenue | E12: $'m | I12: ='Historicals FS'!G9 -> 1553.87 | J12: ='Historicals FS'!H9 -> 1776.88 | K12: ='Historicals FS'!I9 -> 1975.48 | L12: =L146 -> 2145.7711 | M12: =M146 -> 2400.7401 | N12: =N146 -> 2688.7075 | O12: =O146 -> 3012.0125 | P12: =P146 -> 3393.9499
D14: ='Historicals FS'!C11 -> Cost of Sales | E14: $'m | I14: ='Historicals FS'!G11 -> 980.84 | J14: ='Historicals FS'!H11 -> 1078.03 | K14: ='Historicals FS'!I11 -> 1201.29 | L14: =L163 -> 1279.3738 | M14: =M163 -> 1396.86 | N14: =N163 -> 1527.9075 | O14: =O163 -> 1673.1994 | P14: =P163 -> 1843.1964
D15: ='Historicals FS'!C12 -> SG&A | E15: $'m | I15: ='Historicals FS'!G12 -> 265.79 | J15: ='Historicals FS'!H12 -> 290.54 | K15: ='Historicals FS'!I12 -> 305.35 | L15: =L165 -> 320 | M15: =M165 -> 326.4 | N15: =N165 -> 332.928 | O15: =O165 -> 339.58656 | P15: =P165 -> 346.37829
D16: ='Historicals FS'!C13 -> Total Costs | E16: $'m | I16: =SUM(I14:I15) -> 1246.63 | J16: =SUM(J14:J15) -> 1368.57 | K16: =SUM(K14:K15) -> 1506.64 | L16: =SUM(L14:L15) -> 1599.3738 | M16: =SUM(M14:M15) -> 1723.26 | N16: =SUM(N14:N15) -> 1860.8355 | O16: =SUM(O14:O15) -> 2012.7859 | P16: =SUM(P14:P15) -> 2189.5747
D18: ='Historicals FS'!C15 -> Cost Adjustments - Gain/(Loss) | E18: $'m | I18: ='Historicals FS'!G15 -> 0 | J18: ='Historicals FS'!H15 -> 0 | K18: ='Historicals FS'!I15 -> 0 | L18: =Assumptions!L132 -> 0 | M18: =Assumptions!M132 -> 0 | N18: =Assumptions!N132 -> 0 | O18: =Assumptions!O132 -> 0 | P18: =Assumptions!P132 -> 0
D19: ='Historicals FS'!C16 -> EBITDA | E19: $'m | I19: =I12-I16+I18 -> 307.24 | J19: =J12-J16+J18 -> 408.31 | K19: =K12-K16+K18 -> 468.84 | L19: =L12-L16+L18 -> 546.39728 | M19: =M12-M16+M18 -> 677.48014 | N19: =N12-N16+N18 -> 827.87195 | O19: =O12-O16+O18 -> 999.22661 | P19: =P12-P16+P18 -> 1204.3752
D21: ='Historicals FS'!C18 -> Depreciation | E21: $'m | I21: ='Historicals FS'!G18 -> 25.539 | J21: ='Historicals FS'!H18 -> 32.057 | K21: ='Historicals FS'!I18 -> 38.499 | L21: =L187 -> 30.179385 | M21: =M187 -> 32.322242 | N21: =N187 -> 34.4651 | O21: =O187 -> 37.084147 | P21: =P187 -> 40.179385
D22: ='Historicals FS'!C19 -> EBIT | E22: $'m | I22: =I19-I21 -> 281.701 | J22: =J19-J21 -> 376.253 | K22: =K19-K21 -> 430.341 | L22: =L19-L21 -> 516.21789 | M22: =M19-M21 -> 645.15789 | N22: =N19-N21 -> 793.40686 | O22: =O19-O21 -> 962.14246 | P22: =P19-P21 -> 1164.1958
D24: ='Historicals FS'!C21 -> Interest Expense | E24: $'m | I24: ='Historicals FS'!G21 -> 13.304 | J24: ='Historicals FS'!H21 -> 14.263 | K24: ='Historicals FS'!I21 -> 22.055 | L24: =L312 -> 42.724671 | M24: =M312 -> 29.441334 | N24: =N312 -> 9.9110543 | O24: =O312 -> -14.250288 | P24: =P312 -> -44.029926
D25: ='Historicals FS'!C22 -> EBT | E25: $'m | I25: =I22-I24 -> 268.397 | J25: =J22-J24 -> 361.99 | K25: =K22-K24 -> 408.286 | L25: =L22-L24 -> 473.49322 | M25: =M22-M24 -> 615.71656 | N25: =N22-N24 -> 783.4958 | O25: =O22-O24 -> 976.39275 | P25: =P22-P24 -> 1208.2257
D27: ='Historicals FS'!C24 -> Current Taxes | E27: $'m | I27: ='Historicals FS'!G24 -> 62.432 | J27: ='Historicals FS'!H24 -> 92.477 | K27: ='Historicals FS'!I24 -> 100.457 | L27: =L203 -> 151.72263 | M27: =M203 -> 201.5008 | N27: =N203 -> 260.22353 | O27: =O203 -> 327.73746 | P27: =P203 -> 408.879
D28: ='Historicals FS'!C25 -> Deferred Income Taxes | E28: $'m | I28: ='Historicals FS'!G25 -> 9.031 | J28: ='Historicals FS'!H25 -> 2.745 | K28: ='Historicals FS'!I25 -> 10.737 | L28: =L204 -> 14 | M28: =M204 -> 14 | N28: =N204 -> 14 | O28: =O204 -> 14 | P28: =P204 -> 14
D29: ='Historicals FS'!C26 -> Total Income Taxes | E29: $'m | I29: =SUM(I27:I28) -> 71.463 | J29: =SUM(J27:J28) -> 95.222 | K29: =SUM(K27:K28) -> 111.194 | L29: =SUM(L27:L28) -> 165.72263 | M29: =SUM(M27:M28) -> 215.5008 | N29: =SUM(N27:N28) -> 274.22353 | O29: =SUM(O27:O28) -> 341.73746 | P29: =SUM(P27:P28) -> 422.879
D31: ='Historicals FS'!C28 -> Net Income | E31: $'m | I31: =I25-I29 -> 196.934 | J31: =J25-J29 -> 266.768 | K31: =K25-K29 -> 297.092 | L31: =L25-L29 -> 307.7706 | M31: =M25-M29 -> 400.21576 | N31: =N25-N29 -> 509.27227 | O31: =O25-O29 -> 634.65529 | P31: =P25-P29 -> 785.34672
D32: Preference Dividends | E32: $'m | L32: =L252 -> 3.2 | M32: =M252 -> 6.4 | N32: =N252 -> 9.6 | O32: =O252 -> 12.8 | P32: =P252 -> 16
D33: Net Income to Common | E33: $'m | L33: =L31-L32 -> 304.5706 | M33: =M31-M32 -> 393.81576 | N33: =N31-N32 -> 499.67227 | O33: =O31-O32 -> 621.85529 | P33: =P31-P32 -> 769.34672
D35: EBITA Margin | E35: $'m | I35: =I19/I12 -> 0.19772568 | J35: =J19/J12 -> 0.22979042 | K35: =K19/K12 -> 0.23732966 | L35: =L19/L12 -> 0.25463912 | M35: =M19/M12 -> 0.28219636 | N35: =N19/N12 -> 0.30790704 | O35: =O19/O12 -> 0.33174716 | P35: =P19/P12 -> 0.35485945
C36: Dupont Analysis
D37: ROE | E37: $'m | I37: =I31/I114 -> 0.39893204 | J37: =J31/J114 -> 0.85712725 | K37: =K31/K114 -> 4.4437597 | L37: =L31/L114 -> 0.97616957 | M37: =M31/M114 -> 0.63461262 | N37: =N31/N114 -> 0.49665719 | O37: =O31/O114 -> 0.41980347 | P37: =P31/P114 -> 0.37241377
D38: Net Profit Margin | E38: $'m | I38: =I31/I12 -> 0.12673776 | J38: =J31/J12 -> 0.15013282 | K38: =K31/K12 -> 0.15038978 | L38: =L31/L12 -> 0.14343123 | M38: =M31/M12 -> 0.16670516 | N38: =N31/N12 -> 0.18941156 | O38: =O31/O12 -> 0.21070805 | P38: =P31/P12 -> 0.23139609
D39: Asset Turnover | E39: $'m | I39: =I12/I93 -> 1.3639184 | J39: =J12/J93 -> 1.432732 | K39: =K12/K93 -> 1.5489733 | L39: =L12/L93 -> 1.6138316 | M39: =M12/M93 -> 1.7454158 | N39: =N12/N93 -> 1.6739708 | O39: =O12/O93 -> 1.5352803 | P39: =P12/P93 -> 1.3069383
D40: Financial Leverage | E40: $'m | I40: =I93/I114 -> 2.3078336 | J40: =J93/J114 -> 3.9847832 | K40: =K93/K114 -> 19.076044 | L40: =L93/L114 -> 4.2171915 | M40: =M93/M114 -> 2.1810256 | N40: =N93/N114 -> 1.5663989 | O40: =O93/O114 -> 1.2977087 | P40: =P93/P114 -> 1.2314439
B43: Cash Flow Statement
C45: ='Historicals FS'!B36 -> Operating Activities
D46: ='Historicals FS'!C37 -> Net Income | E46: $'m | I46: ='Historicals FS'!G37 -> 196.934 | J46: ='Historicals FS'!H37 -> 266.768 | K46: ='Historicals FS'!I37 -> 297.092 | L46: =L31 -> 307.7706 | M46: =M31 -> 400.21576 | N46: =N31 -> 509.27227 | O46: =O31 -> 634.65529 | P46: =P31 -> 785.34672
D47: ='Historicals FS'!C38 -> Depreciation | E47: $'m | I47: ='Historicals FS'!G38 -> 25.539 | J47: ='Historicals FS'!H38 -> 32.057 | K47: ='Historicals FS'!I38 -> 38.499 | L47: =L21 -> 30.179385 | M47: =M21 -> 32.322242 | N47: =N21 -> 34.4651 | O47: =O21 -> 37.084147 | P47: =P21 -> 40.179385
D48: ='Historicals FS'!C39 -> Deferred Income Taxes | E48: $'m | I48: ='Historicals FS'!G39 -> 9.031 | J48: ='Historicals FS'!H39 -> 2.745 | K48: ='Historicals FS'!I39 -> 10.737 | L48: =L28 -> 14 | M48: =M28 -> 14 | N48: =N28 -> 14 | O48: =O28 -> 14 | P48: =P28 -> 14
D49: ='Historicals FS'!C40 -> Changes in Working Capital | E49: $'m | I49: ='Historicals FS'!G40 -> -5.847 | J49: ='Historicals FS'!H40 -> -19.241 | K49: ='Historicals FS'!I40 -> -2.397 | L49: =L228 -> -61.995582 | M49: =M228 -> -22.01467 | N49: =N228 -> -24.572065 | O49: =O228 -> -26.412414 | P49: =P228 -> -32.762402
D50: Goodwiill Addition/(Impairement) | E50: $'m | L50: =-Assumptions!L134 -> 0 | M50: =-Assumptions!M134 -> 0 | N50: =-Assumptions!N134 -> 0 | O50: =-Assumptions!O134 -> 0 | P50: =-Assumptions!P134 -> 0
D51: ='Historicals FS'!C41 -> Other | E51: $'m | I51: ='Historicals FS'!G41 -> 11.584 | J51: ='Historicals FS'!H41 -> 27.166 | K51: ='Historicals FS'!I41 -> -7.151 | L51: =-Assumptions!L137 -> 0 | M51: =-Assumptions!M137 -> 0 | N51: =-Assumptions!N137 -> 0 | O51: =-Assumptions!O137 -> 0 | P51: =-Assumptions!P137 -> 0
D52: ='Historicals FS'!C42 -> Operating Cash Flow | E52: $'m | I52: =SUM(I46:I51) -> 237.241 | J52: =SUM(J46:J51) -> 309.495 | K52: =SUM(K46:K51) -> 336.78 | L52: =SUM(L46:L51) -> 289.9544 | M52: =SUM(M46:M51) -> 424.52334 | N52: =SUM(N46:N51) -> 533.16531 | O52: =SUM(O46:O51) -> 659.32702 | P52: =SUM(P46:P51) -> 806.7637
C54: ='Historicals FS'!B44 -> Investing Activities
D55: ='Historicals FS'!C45 -> CAPEX | E55: $'m | I55: ='Historicals FS'!G45 -> -56.626 | J55: ='Historicals FS'!H45 -> -62.953 | K55: ='Historicals FS'!I45 -> -110.809 | L55: =-L170 -> -50 | M55: =-M170 -> -40 | N55: =-N170 -> -50 | O55: =-O170 -> -60 | P55: =-P170 -> -70
D56: Intangible Assets | E56: $'m | I56: ='Historicals FS'!G46 -> 0 | J56: ='Historicals FS'!H46 -> 0 | K56: ='Historicals FS'!I46 -> 0 | L56: =-Assumptions!L135 -> 0 | M56: =-Assumptions!M135 -> 0 | N56: =-Assumptions!N135 -> 0 | O56: =-Assumptions!O135 -> 0 | P56: =-Assumptions!P135 -> 0
D57: ='Historicals FS'!C46 -> Other | E57: $'m | I57: ='Historicals FS'!G46 -> 0 | J57: ='Historicals FS'!H46 -> 0 | K57: ='Historicals FS'!I46 -> 0 | L57: =-Assumptions!L138 -> 0 | M57: =-Assumptions!M138 -> 0 | N57: =-Assumptions!N138 -> 0 | O57: =-Assumptions!O138 -> 0 | P57: =-Assumptions!P138 -> 0
D58: ='Historicals FS'!C47 -> Investing Cash Flow | E58: $'m | I58: =SUM(I55:I57) -> -56.626 | J58: =SUM(J55:J57) -> -62.953 | K58: =SUM(K55:K57) -> -110.809 | L58: =SUM(L55:L57) -> -50 | M58: =SUM(M55:M57) -> -40 | N58: =SUM(N55:N57) -> -50 | O58: =SUM(O55:O57) -> -60 | P58: =SUM(P55:P57) -> -70
C60: ='Historicals FS'!B49 -> Financing Activities
D61: ='Historicals FS'!C50 -> Revolver Issuance / (Repayment) | E61: $'m | I61: ='Historicals FS'!G50 -> 10 | J61: ='Historicals FS'!H50 -> 0 | K61: ='Historicals FS'!I50 -> 0 | L61: =L302 -> 42.48325 | M61: =M302 -> -29.669396 | N61: =N302 -> -12.813854 | O61: =O302 -> 0 | P61: =P302 -> 0
D62: ='Historicals FS'!C51 -> Variable Rate Long Term Debt Issuance / (Repayment) | E62: $'m | I62: ='Historicals FS'!G51 -> 100 | J62: ='Historicals FS'!H51 -> 80 | K62: ='Historicals FS'!I51 -> 350 | L62: =-L279 -> -90 | M62: =-M279 -> -90 | N62: =-N279 -> -3.223 | O62: =-O279 -> 0 | P62: =-P279 -> 0
D63: ='Historicals FS'!C52 -> Fixed Rate Long Term Debt Issuance / (Repayment) | E63: $'m | I63: ='Historicals FS'!G52 -> 0 | J63: ='Historicals FS'!H52 -> 156.67 | K63: ='Historicals FS'!I52 -> -80 | L63: =-L272 -> -180 | M63: =-M272 -> -180 | N63: =-N272 -> -180 | O63: =-O272 -> -164.055 | P63: =-P272 -> 0
D64: ='Historicals FS'!C53 -> Preference Shares Issuance/ (Buy-Back) | E64: $'m | I64: ='Historicals FS'!G53 -> 0 | J64: ='Historicals FS'!H53 -> 0 | K64: ='Historicals FS'!I53 -> 0 | L64: =L248 -> 40 | M64: =M248 -> 40 | N64: =N248 -> 40 | O64: =O248 -> 40 | P64: =P248 -> 40
D65: ='Historicals FS'!C54 -> Common Shares Issuance/ (Buy-Back) | E65: $'m | I65: ='Historicals FS'!G54 -> -282.813 | J65: ='Historicals FS'!H54 -> -432.826 | K65: ='Historicals FS'!I54 -> -461.157 | L65: =L241 -> -20 | M65: =M241 -> -20 | N65: =N241 -> -20 | O65: =O241 -> -20 | P65: =P241 -> -20
D66: ='Historicals FS'!C55 -> Preference Dividends | E66: $'m | I66: ='Historicals FS'!G55 -> 0 | J66: ='Historicals FS'!H55 -> 0 | K66: ='Historicals FS'!I55 -> 0 | L66: =-L252 -> -3.2 | M66: =-M252 -> -6.4 | N66: =-N252 -> -9.6 | O66: =-O252 -> -12.8 | P66: =-P252 -> -16
D67: ='Historicals FS'!C56 -> Common Dividends | E67: $'m | I67: ='Historicals FS'!G56 -> -27.89 | J67: ='Historicals FS'!H56 -> -30.077 | K67: ='Historicals FS'!I56 -> -31.291 | L67: =-L257 -> -76.142649 | M67: =-M257 -> -98.453941 | N67: =-N257 -> -124.91807 | O67: =-O257 -> -155.46382 | P67: =-P257 -> -192.33668
D68: ='Historicals FS'!C57 -> Other Financing Activities | E68: $'m | I68: ='Historicals FS'!G57 -> -1.227 | J68: ='Historicals FS'!H57 -> -1.321 | K68: ='Historicals FS'!I57 -> -1.938 | L68: =Assumptions!L136+Assumptions!L139 -> 0 | M68: =Assumptions!M136+Assumptions!M139 -> 0 | N68: =Assumptions!N136+Assumptions!N139 -> 0 | O68: =Assumptions!O136+Assumptions!O139 -> 0 | P68: =Assumptions!P136+Assumptions!P139 -> 0
D69: ='Historicals FS'!C58 -> Financing Cash Flow | E69: $'m | I69: =SUM(I61:I68) -> -201.93 | J69: =SUM(J61:J68) -> -227.554 | K69: =SUM(K61:K68) -> -224.386 | L69: =SUM(L61:L68) -> -286.8594 | M69: =SUM(M61:M68) -> -384.52334 | N69: =SUM(N61:N68) -> -310.55492 | O69: =SUM(O61:O68) -> -312.31882 | P69: =SUM(P61:P68) -> -188.33668
D71: ='Historicals FS'!C60 -> Change in Cash Position | E71: $'m | I71: =SUM(I69,I58,I52) -> -21.315 | J71: =SUM(J69,J58,J52) -> 18.988 | K71: =SUM(K69,K58,K52) -> 1.585 | L71: =SUM(L69,L58,L52) -> -46.905 | M71: =SUM(M69,M58,M52) -> 0 | N71: =SUM(N69,N58,N52) -> 172.61038 | O71: =SUM(O69,O58,O52) -> 287.0082 | P71: =SUM(P69,P58,P52) -> 548.42702
D72: ='Historicals FS'!C61 -> Beginning Cash | E72: $'m | I72: ='Historicals FS'!G61 -> 47.647 | J72: ='Historicals FS'!H61 -> 26.332 | K72: ='Historicals FS'!I61 -> 45.32 | L72: =K73 -> 46.905 | M72: =L73 -> 0 | N72: =M73 -> 0 | O72: =N73 -> 172.61038 | P72: =O73 -> 459.61858
D73: ='Historicals FS'!C62 -> Ending Cash | E73: $'m | I73: ='Historicals FS'!G62 -> 26.332 | J73: ='Historicals FS'!H62 -> 45.32 | K73: ='Historicals FS'!I62 -> 46.905 | L73: =SUM(L71:L72) -> 0 | M73: =SUM(M71:M72) -> 0 | N73: =SUM(N71:N72) -> 172.61038 | O73: =SUM(O71:O72) -> 459.61858 | P73: =SUM(P71:P72) -> 1008.0456
B77: Balance Sheet
C79: ='Historicals FS'!B72 -> ASSETS
D80: ='Historicals FS'!C73 -> Cash and Equivalents | E80: $'m | I80: ='Historicals FS'!G73 -> 26.332 | J80: ='Historicals FS'!H73 -> 45.32 | K80: ='Historicals FS'!I73 -> 46.905 | L80: =L73 -> 0 | M80: =M73 -> 0 | N80: =N73 -> 172.61038 | O80: =O73 -> 459.61858 | P80: =P73 -> 1008.0456
D81: ='Historicals FS'!C74 -> Accounts Receivable | E81: $'m | I81: ='Historicals FS'!G74 -> 6.669 | J81: ='Historicals FS'!H74 -> 7.412 | K81: ='Historicals FS'!I74 -> 10.257 | L81: =L218 -> 9.776486 | M81: =M218 -> 10.938167 | N81: =N218 -> 12.250193 | O81: =O218 -> 13.685729 | P81: =P218 -> 15.463394
D82: ='Historicals FS'!C75 -> Inventory | E82: $'m | I82: ='Historicals FS'!G75 -> 272.613 | J82: ='Historicals FS'!H75 -> 313.463 | K82: ='Historicals FS'!I75 -> 310.477 | L82: =L219 -> 353.08966 | M82: =M219 -> 385.51423 | N82: =N219 -> 421.68155 | O82: =O219 -> 460.51841 | P82: =P219 -> 508.69696
D83: ='Historicals FS'!C76 -> Prepaid Expenses | E83: $'m | I83: ='Historicals FS'!G76 -> 0 | J83: ='Historicals FS'!H76 -> 0 | K83: ='Historicals FS'!I76 -> 0 | L83: =L220 -> 0 | M83: =M220 -> 0 | N83: =N220 -> 0 | O83: =O220 -> 0 | P83: =P220 -> 0
D84: ='Historicals FS'!C77 -> Other | E84: $'m | I84: ='Historicals FS'!G77 -> 59.481 | J84: ='Historicals FS'!H77 -> 50.961 | K84: ='Historicals FS'!I77 -> 10.633 | L84: =L221 -> 49.850013 | M84: =M221 -> 54.427789 | N84: =N221 -> 59.533975 | O84: =O221 -> 65.017053 | P84: =P221 -> 71.819012
D85: ='Historicals FS'!C78 -> Total Current Assets | E85: $'m | I85: =SUM(I80:I84) -> 365.095 | J85: =SUM(J80:J84) -> 417.156 | K85: =SUM(K80:K84) -> 378.272 | L85: =SUM(L80:L84) -> 412.71616 | M85: =SUM(M80:M84) -> 450.88018 | N85: =SUM(N80:N84) -> 666.0761 | O85: =SUM(O80:O84) -> 998.83977 | P85: =SUM(P80:P84) -> 1604.025
D87: ='Historicals FS'!C80 -> Net PP&E | E87: $'m | I87: ='Historicals FS'!G80 -> 199.602 | J87: ='Historicals FS'!H80 -> 246.571 | K87: ='Historicals FS'!I80 -> 318.878 | L87: =K87-L55-L47 -> 338.69861 | M87: =L87-M55-M47 -> 346.37637 | N87: =M87-N55-N47 -> 361.91127 | O87: =N87-O55-O47 -> 384.82713 | P87: =O87-P55-P47 -> 414.64774
D88: ='Historicals FS'!C81 -> Goodwill | E88: $'m | I88: ='Historicals FS'!G81 -> 485.188 | J88: ='Historicals FS'!H81 -> 485.188 | K88: ='Historicals FS'!I81 -> 485.188 | L88: =K88+Assumptions!L134 -> 485.188 | M88: =L88+Assumptions!M134 -> 485.188 | N88: =M88+Assumptions!N134 -> 485.188 | O88: =N88+Assumptions!O134 -> 485.188 | P88: =O88+Assumptions!P134 -> 485.188
D89: ='Historicals FS'!C82 -> Intangibles | E89: $'m | I89: ='Historicals FS'!G82 -> 89.384 | J89: ='Historicals FS'!H82 -> 91.289 | K89: ='Historicals FS'!I82 -> 93.01 | L89: =K89+Assumptions!L135 -> 93.01 | M89: =L89+Assumptions!M135 -> 93.01 | N89: =M89+Assumptions!N135 -> 93.01 | O89: =N89+Assumptions!O135 -> 93.01 | P89: =O89+Assumptions!P135 -> 93.01
D90: ='Historicals FS'!C83 -> Other | E90: $'m | I90: ='Historicals FS'!G83 -> 0 | J90: ='Historicals FS'!H83 -> 0 | K90: ='Historicals FS'!I83 -> 0 | L90: =K90+Assumptions!L138 -> 0 | M90: =L90+Assumptions!M138 -> 0 | N90: =M90+Assumptions!N138 -> 0 | O90: =N90+Assumptions!O138 -> 0 | P90: =O90+Assumptions!P138 -> 0
D91: ='Historicals FS'!C84 -> Total Long Term Assets | E91: $'m | I91: =SUM(I87:I90) -> 774.174 | J91: =SUM(J87:J90) -> 823.048 | K91: =SUM(K87:K90) -> 897.076 | L91: =SUM(L87:L90) -> 916.89661 | M91: =SUM(M87:M90) -> 924.57437 | N91: =SUM(N87:N90) -> 940.10927 | O91: =SUM(O87:O90) -> 963.02513 | P91: =SUM(P87:P90) -> 992.84574
D93: ='Historicals FS'!C86 -> Total Assets | E93: $'m | I93: =I85+I91 -> 1139.269 | J93: =J85+J91 -> 1240.204 | K93: =K85+K91 -> 1275.348 | L93: =L85+L91 -> 1329.6128 | M93: =M85+M91 -> 1375.4546 | N93: =N85+N91 -> 1606.1854 | O93: =O85+O91 -> 1961.8649 | P93: =P85+P91 -> 2596.8707
C96: ='Historicals FS'!B88 -> LIABILITIES AND EQUITY
D97: ='Historicals FS'!C89 -> Bank Debt - Revolver | E97: $'m | I97: ='Historicals FS'!G89 -> 10 | J97: ='Historicals FS'!H89 -> 0 | K97: ='Historicals FS'!I89 -> 0 | L97: =L303 -> 42.48325 | M97: =M303 -> 12.813854 | N97: =N303 -> 0 | O97: =O303 -> 0 | P97: =P303 -> 0
D98: ='Historicals FS'!C90 -> Accounts Payable | E98: $'m | I98: ='Historicals FS'!G90 -> 117.159 | J98: ='Historicals FS'!H90 -> 110.781 | K98: ='Historicals FS'!I90 -> 132.324 | L98: =L223 -> 141.85978 | M98: =M223 -> 154.8869 | N98: =N223 -> 169.41774 | O98: =O223 -> 185.0211 | P98: =P223 -> 204.37766
D99: ='Historicals FS'!C91 -> Other | E99: $'m | I99: ='Historicals FS'!G91 -> 23.596 | J99: ='Historicals FS'!H91 -> 38.209 | K99: ='Historicals FS'!I91 -> 24.182 | L99: =L224 -> 33.999798 | M99: =M224 -> 37.122033 | N99: =N224 -> 40.604666 | O99: =O224 -> 44.344355 | P99: =P224 -> 48.983576
D100: ='Historicals FS'!C92 -> Total Current Liabilities | E100: $'m | I100: =SUM(I97:I99) -> 150.755 | J100: =SUM(J97:J99) -> 148.99 | K100: =SUM(K97:K99) -> 156.506 | L100: =SUM(L97:L99) -> 218.34282 | M100: =SUM(M97:M99) -> 204.82279 | N100: =SUM(N97:N99) -> 210.0224 | O100: =SUM(O97:O99) -> 229.36546 | P100: =SUM(P97:P99) -> 253.36123
D102: ='Historicals FS'!C94 -> Variable Rate Long Term Debt | E102: $'m | I102: ='Historicals FS'!G94 -> 100 | J102: ='Historicals FS'!H94 -> 185.584 | K102: ='Historicals FS'!I94 -> 183.223 | L102: =L280 -> 93.223 | M102: =M280 -> 3.223 | N102: =N280 -> 0 | O102: =O280 -> 0 | P102: =P280 -> 0
D103: ='Historicals FS'!C95 -> Fixed Rate Long Term Debt | E103: $'m | I103: ='Historicals FS'!G95 -> 260.46 | J103: ='Historicals FS'!H95 -> 422.829 | K103: ='Historicals FS'!I95 -> 704.055 | L103: =L273 -> 524.055 | M103: =M273 -> 344.055 | N103: =N273 -> 164.055 | O103: =O273 -> 0 | P103: =P273 -> 0
D104: ='Historicals FS'!C96 -> Deferred Income Taxes | E104: $'m | I104: ='Historicals FS'!G96 -> 93.04 | J104: ='Historicals FS'!H96 -> 123.811 | K104: ='Historicals FS'!I96 -> 110.157 | L104: =K104+L48 -> 124.157 | M104: =L104+M48 -> 138.157 | N104: =M104+N48 -> 152.157 | O104: =N104+O48 -> 166.157 | P104: =O104+P48 -> 180.157
D105: ='Historicals FS'!C97 -> Other | E105: $'m | I105: ='Historicals FS'!G97 -> 41.361 | J105: ='Historicals FS'!H97 -> 47.755 | K105: ='Historicals FS'!I97 -> 54.551 | L105: =K105+Assumptions!L139 -> 54.551 | M105: =L105+Assumptions!M139 -> 54.551 | N105: =M105+Assumptions!N139 -> 54.551 | O105: =N105+Assumptions!O139 -> 54.551 | P105: =O105+Assumptions!P139 -> 54.551
D106: ='Historicals FS'!C98 -> Total Long Term Liabilities | E106: $'m | I106: =SUM(I102:I105) -> 494.861 | J106: =SUM(J102:J105) -> 779.979 | K106: =SUM(K102:K105) -> 1051.986 | L106: =SUM(L102:L105) -> 795.986 | M106: =SUM(M102:M105) -> 539.986 | N106: =SUM(N102:N105) -> 370.763 | O106: =SUM(O102:O105) -> 220.708 | P106: =SUM(P102:P105) -> 234.708
D108: ='Historicals FS'!C100 -> Total Liabilities | E108: $'m | I108: =I100+I106 -> 645.616 | J108: =J100+J106 -> 928.969 | K108: =K100+K106 -> 1208.492 | L108: =L100+L106 -> 1014.3288 | M108: =M100+M106 -> 744.80879 | N108: =N100+N106 -> 580.7854 | O108: =O100+O106 -> 450.07346 | P108: =P100+P106 -> 488.06923
D110: ='Historicals FS'!C102 -> Preference Shares | E110: $'m | I110: ='Historicals FS'!G102 -> 0 | J110: ='Historicals FS'!H102 -> 0 | K110: ='Historicals FS'!I102 -> 0 | L110: =L249 -> 40 | M110: =M249 -> 80 | N110: =N249 -> 120 | O110: =O249 -> 160 | P110: =P249 -> 200
D111: ='Historicals FS'!C103 -> Common Shares | E111: $'m | I111: ='Historicals FS'!G103 -> 308.489 | J111: ='Historicals FS'!H103 -> 292.864 | K111: ='Historicals FS'!I103 -> 280.177 | L111: =L242 -> 260.177 | M111: =M242 -> 240.177 | N111: =N242 -> 220.177 | O111: =O242 -> 200.177 | P111: =P242 -> 180.177
D112: ='Historicals FS'!C104 -> Retained Earnings | E112: $'m | I112: ='Historicals FS'!G104 -> 130.741 | J112: ='Historicals FS'!H104 -> -41.583 | K112: ='Historicals FS'!I104 -> -228.638 | L112: =L258 -> -0.21005369 | M112: =M258 -> 295.15177 | N112: =N258 -> 669.90597 | O112: =O258 -> 1136.2974 | P112: =P258 -> 1713.3075
D113: ='Historicals FS'!C105 -> Other | E113: $'m | I113: ='Historicals FS'!G105 -> 54.423 | J113: ='Historicals FS'!H105 -> 59.954 | K113: ='Historicals FS'!I105 -> 15.317 | L113: =K113+Assumptions!L136 -> 15.317 | M113: =L113+Assumptions!M136 -> 15.317 | N113: =M113+Assumptions!N136 -> 15.317 | O113: =N113+Assumptions!O136 -> 15.317 | P113: =O113+Assumptions!P136 -> 15.317
D114: ='Historicals FS'!C106 -> Shareholder's Equity | E114: $'m | I114: =SUM(I110:I113) -> 493.653 | J114: =SUM(J110:J113) -> 311.235 | K114: =SUM(K110:K113) -> 66.856 | L114: =SUM(L110:L113) -> 315.28395 | M114: =SUM(M110:M113) -> 630.64577 | N114: =SUM(N110:N113) -> 1025.4 | O114: =SUM(O110:O113) -> 1511.7914 | P114: =SUM(P110:P113) -> 2108.8015
C116: ='Historicals FS'!B108 -> Total Liabilities and Equity | I116: =I108+I114 -> 1139.269 | J116: =J108+J114 -> 1240.204 | K116: =K108+K114 -> 1275.348 | L116: =L108+L114 -> 1329.6128 | M116: =M108+M114 -> 1375.4546 | N116: =N108+N114 -> 1606.1854 | O116: =O108+O114 -> 1961.8649 | P116: =P108+P114 -> 2596.8707
D118: Accuracy Check | F118: =ROUND(SUM(I118:P118),4) -> 0 | I118: =I116-I93 -> 0 | J118: =J116-J93 -> 0 | K118: =K116-K93 -> 0 | L118: =L116-L93 -> 0 | M118: =M116-M93 -> 0 | N118: =N116-N93 -> 0 | O118: =O116-O93 -> 0 | P118: =P116-P93 -> 0
A121: SCHEDULES & CALCULATIONS
B123: Revenue Schedule
D125: Sales Price inflation Rate | E125: % | L125: =Assumptions!L39 -> 0.03 | M125: =Assumptions!M39 -> 0.03 | N125: =Assumptions!N39 -> 0.03 | O125: =Assumptions!O39 -> 0.03 | P125: =Assumptions!P39 -> 0.03
D126: New Warehouses | E126: units | L126: =Assumptions!L41 -> 30 | M126: =Assumptions!M41 -> 50 | N126: =Assumptions!N41 -> 55 | O126: =Assumptions!O41 -> 60 | P126: =Assumptions!P41 -> 70
C128: Sales Price
D130: Gross Sales Price per sqm | E130: $/sqm | K130: =Assumptions!K37 -> 352.06148 | L130: =K130*(1+L125) -> 362.62332 | M130: =L130*(1+M125) -> 373.50202 | N130: =M130*(1+N125) -> 384.70708 | O130: =N130*(1+O125) -> 396.2483 | P130: =O130*(1+P125) -> 408.13575
C132: Sales Volume
D134: Additional Warehouses | E134: Units | L134: =L126 -> 30 | M134: =M126 -> 50 | N134: =N126 -> 55 | O134: =O126 -> 60 | P134: =P126 -> 70
D135: Warehouses Forecast | E135: Units | K135: =Assumptions!K31 -> 510 | L135: =K135+L134 -> 540 | M135: =L135+M134 -> 590 | N135: =M135+N134 -> 645 | O135: =N135+O134 -> 705 | P135: =O135+P134 -> 775
D136: Square Meters per store | E136: sqm | K136: =Assumptions!K33 -> 10205.882 | L136: =$K$136 -> 10205.882 | M136: =$K$136 -> 10205.882 | N136: =$K$136 -> 10205.882 | O136: =$K$136 -> 10205.882 | P136: =$K$136 -> 10205.882
D138: Total Lettable Space in Sqm | E138: sqm | K138: =K136*K135 -> 5205000 | L138: =L136*L135 -> 5511176.5 | M138: =M136*M135 -> 6021470.6 | N138: =N136*N135 -> 6582794.1 | O138: =O136*O135 -> 7195147.1 | P138: =P136*P135 -> 7909558.8
C140: Auxillary Revenue | E140: $'m | K140: =Assumptions!K35 -> 143 | L140: =K140*(1+L125) -> 147.29 | M140: =L140*(1+M125) -> 151.7087 | N140: =M140*(1+N125) -> 156.25996 | O140: =N140*(1+O125) -> 160.94776 | P140: =O140*(1+P125) -> 165.77619
C142: Revenue
...
